[
  {
    "start": 0.0,
    "text": "Der Kapitel das ich lese heißt Al Insan und das ist der 76 Kapitel aus dem Kuran."
  },
  {
    "start": 10.0,
    "text": "Ich suche Schutz bei Gott, vor dem Teufel der verflucht ist."
  },
  {
    "start": 14.0,
    "text": "Und ich Spreche im Namen von Gott, dem Liebevoll und dem Barmherzigen."
  },
  {
    "start": 17.0,
    "text": "Caut protecție la Dumnezeu împotriva diavolului, care este blestemat."
  },
  {
    "start": 21.0,
    "text": "În Numele lui Dumnezeu, Cel Iubitor, Cel Milostiv."
  }
]